LICENSE
MANIFEST.in
README.md
setup.py
src/BUDEFF.egg-info/PKG-INFO
src/BUDEFF.egg-info/SOURCES.txt
src/BUDEFF.egg-info/dependency_links.txt
src/BUDEFF.egg-info/not-zip-safe
src/BUDEFF.egg-info/requires.txt
src/BUDEFF.egg-info/top_level.txt
src/budeff/__init__.py
src/budeff/calculateEnergies.cpp
src/budeff/calculate_energy.cpp
src/budeff/calculate_energy.pyx
src/budeff/dataClasses.hpp
src/budeff/force_field.py
src/budeff/force_fields/bude_2015v1.json
src/budeff/force_fields/bude_2016v1.json