Metadata-Version: 2.1
Name: BUDEFF
Version: 1.0.0
Summary: A Python implementation of the BUDE force field.
Home-page: https://github.com/isambard-uob/buff
Author: Woolfson Group, University of Bristol
Author-email: chris.wood@bristol.ac.uk
License: UNKNOWN
Platform: UNKNOWN
Classifier: Intended Audience :: Science/Research
Classifier: License :: OSI Approved :: MIT License
Classifier: Natural Language :: English
Classifier: Topic :: Scientific/Engineering :: Bio-Informatics
Classifier: Programming Language :: Python :: 3.5
Classifier: Programming Language :: Python :: 3.6
